dora_reachy2/__init__.py
dora_reachy2/camera.py
dora_reachy2/head.py
dora_reachy2/left_arm.py
dora_reachy2/mobile_base.py
dora_reachy2/right_arm.py
dora_reachy2-0.4.1.dist-info/METADATA
dora_reachy2-0.4.1.dist-info/WHEEL
dora_reachy2-0.4.1.dist-info/entry_points.txt
dora_reachy2-0.4.1.dist-info/top_level.txt
dora_reachy2-0.4.1.dist-info/RECORD
