Metadata-Version: 2.4
Name: dora-reachy2
Version: 0.4.1
Summary: dora-reachy2
Author-email: Your Name <email@email.com>
License: MIT
Requires-Python: >=3.10
Requires-Dist: dora-rs>=0.3.9
Requires-Dist: reachy2-sdk==1.0.7
Requires-Dist: reachy2-sdk-api==1.0.15
Requires-Dist: scipy
